{"34": {"becameSuitTime": 1474824037.258, "savedBy": null, "track": "c", "numFloors": "5", "difficulty": "6", "state": "suit", "block": "34"}, "41": {"becameSuitTime": 1474824533.737, "savedBy": null, "track": "c", "numFloors": "3", "difficulty": "5", "state": "suit", "block": "41"}, "43": {"becameSuitTime": 1474824138.878, "savedBy": null, "track": "c", "numFloors": "3", "difficulty": "4", "state": "suit", "block": "43"}, "12": {"becameSuitTime": 1474824443.962, "savedBy": null, "track": "c", "numFloors": "3", "difficulty": "6", "state": "suit", "block": "12"}, "15": {"becameSuitTime": 1474823850.174, "savedBy": null, "track": "c", "numFloors": "3", "difficulty": "6", "state": "suit", "block": "15"}, "49": {"becameSuitTime": 1474824355.034, "savedBy": null, "track": "c", "numFloors": "5", "difficulty": "6", "state": "suit", "block": "49"}, "50": {"becameSuitTime": 1474823850.175, "savedBy": null, "track": "c", "numFloors": "4", "difficulty": "5", "state": "suit", "block": "50"}, "51": {"becameSuitTime": 1474824021.05, "savedBy": null, "track": "c", "numFloors": "3", "difficulty": "4", "state": "suit", "block": "51"}, "24": {"becameSuitTime": 1474823850.174, "savedBy": null, "track": "c", "numFloors": "3", "difficulty": "5", "state": "suit", "block": "24"}, "44": {"becameSuitTime": 1474824358.822, "savedBy": null, "track": "c", "numFloors": "3", "difficulty": "6", "state": "suit", "block": "44"}}